torch_tiltxcorr/__init__.py
torch_tiltxcorr/tiltxcorr.py
torch_tiltxcorr/tiltxcorr_no_stretch.py
torch_tiltxcorr/tiltxcorr_with_sample_tilt_estimation.py
torch_tiltxcorr/utils.py
torch_tiltxcorr-0.1.4.dist-info/METADATA
torch_tiltxcorr-0.1.4.dist-info/WHEEL
torch_tiltxcorr-0.1.4.dist-info/licenses/LICENSE
torch_tiltxcorr-0.1.4.dist-info/RECORD
