Metadata-Version: 2.4
Name: torch-tiltxcorr
Version: 0.1.4
Summary: Cross correlation with cosine stretching for cryo-EM data in PyTorch
Project-URL: homepage, https://github.com/teamtomo/torch-tiltxcorr
Project-URL: repository, https://github.com/teamtomo/torch-tiltxcorr
Author-email: Alister Burt <alisterburt@gmail.com>
License: BSD-3-Clause
License-File: LICENSE
Classifier: Development Status :: 3 - Alpha
Classifier: License :: OSI Approved :: BSD License
Classifier: Programming Language :: Python :: 3
Classifier: Programming Language :: Python :: 3.10
Classifier: Programming Language :: Python :: 3.11
Classifier: Programming Language :: Python :: 3.12
Classifier: Programming Language :: Python :: 3.13
Classifier: Typing :: Typed
Requires-Python: >=3.10
Requires-Dist: einops
Requires-Dist: numpy
Requires-Dist: scipy
Requires-Dist: torch
Requires-Dist: torch-affine-utils
Requires-Dist: torch-fourier-filter
Requires-Dist: torch-fourier-rescale
Requires-Dist: torch-transform-image
Provides-Extra: dev
Requires-Dist: ipython; extra == 'dev'
Requires-Dist: pdbpp; extra == 'dev'
Requires-Dist: rich; extra == 'dev'
Provides-Extra: test
Requires-Dist: pytest; extra == 'test'
Requires-Dist: pytest-cov; extra == 'test'
Requires-Dist: torch-fourier-shift; extra == 'test'
Requires-Dist: torch-fourier-slice; extra == 'test'
